amangkurat/__init__.py
amangkurat/cli.py
amangkurat/core/__init__.py
amangkurat/core/initial_conditions.py
amangkurat/core/solver.py
amangkurat/io/__init__.py
amangkurat/io/config_manager.py
amangkurat/io/data_handler.py
amangkurat/utils/__init__.py
amangkurat/utils/logger.py
amangkurat/utils/timer.py
amangkurat/visualization/__init__.py
amangkurat/visualization/animator.py
amangkurat-0.0.1.dist-info/LICENSE
amangkurat-0.0.1.dist-info/METADATA
amangkurat-0.0.1.dist-info/WHEEL
amangkurat-0.0.1.dist-info/entry_points.txt
amangkurat-0.0.1.dist-info/RECORD
